odoo/addons/base_business_document_import_phone/README.rst
odoo/addons/base_business_document_import_phone/__init__.py
odoo/addons/base_business_document_import_phone/__manifest__.py
odoo/addons/base_business_document_import_phone/i18n/base_business_document_import_phone.pot
odoo/addons/base_business_document_import_phone/i18n/de.po
odoo/addons/base_business_document_import_phone/i18n/es.po
odoo/addons/base_business_document_import_phone/i18n/hr.po
odoo/addons/base_business_document_import_phone/i18n/it.po
odoo/addons/base_business_document_import_phone/models/__init__.py
odoo/addons/base_business_document_import_phone/models/business_document_import.py
odoo/addons/base_business_document_import_phone/readme/CONTRIBUTORS.rst
odoo/addons/base_business_document_import_phone/readme/DESCRIPTION.rst
odoo/addons/base_business_document_import_phone/readme/INSTALL.rst
odoo/addons/base_business_document_import_phone/static/description/icon.png
odoo/addons/base_business_document_import_phone/static/description/index.html
odoo/addons/base_business_document_import_phone/tests/__init__.py
odoo/addons/base_business_document_import_phone/tests/test_phone_partner_match.py
odoo14_addon_base_business_document_import_phone-14.0.1.0.1.dev11.dist-info/METADATA
odoo14_addon_base_business_document_import_phone-14.0.1.0.1.dev11.dist-info/WHEEL
odoo14_addon_base_business_document_import_phone-14.0.1.0.1.dev11.dist-info/top_level.txt
odoo14_addon_base_business_document_import_phone-14.0.1.0.1.dev11.dist-info/RECORD
