Metadata-Version: 2.1
Name: odoo14-addon-base_business_document_import_phone
Version: 14.0.1.0.1.dev11
Summary: Use phone numbers to match partners upon import of business documents
Home-page: https://github.com/OCA/edi
Author: Akretion,Odoo Community Association (OCA)
Author-email: support@odoo-community.org
License: AGPL-3
Classifier: Programming Language :: Python
Classifier: Framework :: Odoo
Classifier: Framework :: Odoo :: 14.0
Classifier: License :: OSI Approved :: GNU Affero General Public License v3
Requires-Python: >=3.6
Requires-Dist: odoo14-addon-base-business-document-import
Requires-Dist: odoo<14.1dev,>=14.0a
Requires-Dist: phonenumbers
